deezer_dl/__init__.py
deezer_dl/base.py
deezer_dl/deezer.py
deezer_dl/deezer_dl.py
deezer_dl/logging.py
deezer_dl/model.py
deezer_dl/utils.py
deezer_dl-1.0.1.dist-info/LICENSE
deezer_dl-1.0.1.dist-info/METADATA
deezer_dl-1.0.1.dist-info/WHEEL
deezer_dl-1.0.1.dist-info/entry_points.txt
deezer_dl-1.0.1.dist-info/top_level.txt
deezer_dl-1.0.1.dist-info/RECORD
