Metadata-Version: 2.1
Name: deezer-dl
Version: 1.0.1
Summary: Download songs from Deezer
Home-page: https://github.com/doulwyi/deezer-dl
Author: Bruno Kanazawa
Author-email: kanazawabruno@gmail.com
License: UNKNOWN
Platform: UNKNOWN
Classifier: Programming Language :: Python :: 3
Classifier: License :: OSI Approved :: MIT License
Classifier: Operating System :: OS Independent
Requires-Python: >=3
Requires-Dist: SQLAlchemy (==1.2.14)
Requires-Dist: cachetools (==3.0.0)
Requires-Dist: certifi (==2018.11.29)
Requires-Dist: chardet (==3.0.4)
Requires-Dist: google-api-python-client (==1.7.4)
Requires-Dist: google-auth-httplib2 (==0.0.3)
Requires-Dist: google-auth (==1.6.1)
Requires-Dist: httplib2 (==0.12.0)
Requires-Dist: idna (==2.7)
Requires-Dist: pyasn1-modules (==0.2.2)
Requires-Dist: pyasn1 (==0.4.4)
Requires-Dist: pydub (==0.23.0)
Requires-Dist: pytube
Requires-Dist: requests (==2.20.1)
Requires-Dist: rsa (==4.0)
Requires-Dist: six (==1.11.0)
Requires-Dist: tqdm (==4.28.1)
Requires-Dist: uritemplate (==3.0.0)
Requires-Dist: urllib3 (==1.24.1)
